.testr.conf
AUTHORS
ChangeLog
LICENSE
README.md
VERSION
requirements.txt
setup.cfg
setup.py
test-requirements.txt
tox.ini
debian/changelog
debian/compat
debian/control
debian/rules
debian/source/format
examples/client-example.py
warp10client/__init__.py
warp10client/client.py
warp10client/metric.py
warp10client/position.py
warp10client/timeserie.py
warp10client.egg-info/PKG-INFO
warp10client.egg-info/SOURCES.txt
warp10client.egg-info/dependency_links.txt
warp10client.egg-info/not-zip-safe
warp10client.egg-info/pbr.json
warp10client.egg-info/requires.txt
warp10client.egg-info/top_level.txt
warp10client/common/__init__.py
warp10client/common/constants.py
warp10client/tests/__init__.py
warp10client/tests/base.py
warp10client/tests/unit/__init__.py
warp10client/tests/unit/test_client.py