Metadata-Version: 1.1
Name: warp10client
Version: 1.0.1.dev3
Summary: OVH Python Warp10 Client
Home-page: https://www.ovh.com/cloud/
Author: OVH
Author-email: dev@cloud.ovh.net
License: UNKNOWN
Platform: UNKNOWN
Classifier: Intended Audience :: Information Technology
Classifier: Intended Audience :: System Administrators
Classifier: License :: OSI Approved :: Apache Software License
Classifier: Operating System :: POSIX :: Linux
Classifier: Programming Language :: Python
Classifier: Programming Language :: Python :: 2
Classifier: Programming Language :: Python :: 2.7
Classifier: Programming Language :: Python :: 3
Classifier: Programming Language :: Python :: 3.4
